README
setup.py
pymget/__init__.py
pymget/command_line.py
pymget/console.py
pymget/data_queue.py
pymget/errors.py
pymget/manager.py
pymget/messages.py
pymget/mirrors.py
pymget/networking.py
pymget/outfile.py
pymget/pymget.py
pymget/task_info.py
pymget/utils.py
pymget.egg-info/PKG-INFO
pymget.egg-info/SOURCES.txt
pymget.egg-info/dependency_links.txt
pymget.egg-info/entry_points.txt
pymget.egg-info/requires.txt
pymget.egg-info/top_level.txt
pymget/i18n/ru/LC_MESSAGES/messages.mo
pymget/i18n/uk/LC_MESSAGES/messages.mo