Metadata-Version: 1.0
Name: pymget
Version: 1.42
Summary: Utility for parallel downloading files from multiple mirrors
Home-page: http://pymget.sourceforge.net/
Author: Taras Gaidukov
Author-email: kemaweyan@gmail.com
License: GPLv3
Keywords: downloading mirros parallel
Platform: UNKNOWN
